Metadata-Version: 2.1
Name: odoo-addon-l10n_it_website_portal_fatturapa
Version: 16.0.1.0.0.7
Requires-Python: >=3.10
Requires-Dist: odoo-addon-l10n_it_fatturapa>=16.0dev,<16.1dev
Requires-Dist: odoo-addon-l10n_it_website_portal_fiscalcode>=16.0dev,<16.1dev
Requires-Dist: odoo-addon-l10n_it_website_portal_ipa>=16.0dev,<16.1dev
Requires-Dist: odoo>=16.0a,<16.1dev
Summary: Add fatturapa fields and checks in frontend user's details
Home-page: https://github.com/OCA/l10n-italy/tree/16.0/l10n_it_website_portal_fatturapa
License: AGPL-3
Author: Odoo Community Association (OCA)
Author-email: support@odoo-community.org
Classifier: Programming Language :: Python
Classifier: Framework :: Odoo
Classifier: Framework :: Odoo :: 16.0
Classifier: License :: OSI Approved :: GNU Affero General Public License v3
